{
  "cookies": [
    {
      "name": "datr",
      "value": "XBr1Z-P5u2xzf-4lQNTcZrrU",
      "domain": ".facebook.com",
      "path": "/",
      "expires": 1778676325.109462,
      "httpOnly": true,
      "secure": true,
      "sameSite": "None"
    },
    {
      "name": "sb",
      "value": "XBr1Z4qX-t2zDbnSjzQ-fO5b",
      "domain": ".facebook.com",
      "path": "/",
      "expires": 1778676349.703539,
      "httpOnly": true,
      "secure": true,
      "sameSite": "None"
    },
    {
      "name": "locale",
      "value": "fr_FR",
      "domain": ".facebook.com",
      "path": "/",
      "expires": 1744721125.10953,
      "httpOnly": false,
      "secure": true,
      "sameSite": "None"
    },
    {
      "name": "wd",
      "value": "1280x720",
      "domain": ".facebook.com",
      "path": "/",
      "expires": 1744721156,
      "httpOnly": false,
      "secure": true,
      "sameSite": "Lax"
    },
    {
      "name": "dpr",
      "value": "1",
      "domain": ".facebook.com",
      "path": "/",
      "expires": 1744721156,
      "httpOnly": false,
      "secure": true,
      "sameSite": "None"
    },
    {
      "name": "c_user",
      "value": "100004076987599",
      "domain": ".facebook.com",
      "path": "/",
      "expires": -1,
      "httpOnly": false,
      "secure": true,
      "sameSite": "None"
    },
    {
      "name": "xs",
      "value": "11%3A0ddjFWwd_ISMxQ%3A2%3A1744116345%3A-1%3A11679",
      "domain": ".facebook.com",
      "path": "/",
      "expires": -1,
      "httpOnly": true,
      "secure": true,
      "sameSite": "None"
    },
    {
      "name": "fr",
      "value": "0r92ut1eaCJ4zy3CI.AWfs2C4wzDnSB03IFNubJHQDYg_1gybexHhk7USbmvopw9bLNjE.Bn9RqA..AAA.0.0.Bn9RqA.AWdjCoOTXP5x0q8Vzb3X13lhZ9E",
      "domain": ".facebook.com",
      "path": "/",
      "expires": 1751892353.199283,
      "httpOnly": true,
      "secure": true,
      "sameSite": "None"
    },
    {
      "name": "presence",
      "value": "C%7B%22t3%22%3A%5B%5D%2C%22utc3%22%3A1744116357053%2C%22v%22%3A1%7D",
      "domain": ".facebook.com",
      "path": "/",
      "expires": -1,
      "httpOnly": false,
      "secure": true,
      "sameSite": "Lax"
    }
  ],
  "origins": [
    {
      "origin": "https://www.facebook.com",
      "localStorage": [
        {
          "name": "screen_time_period_logging_facebook",
          "value": "{\"actorId\":\"100004076987599\",\"currentIntervalLastTick\":1744116418,\"currentIntervalStart\":1744116350,\"initRemoteAgg\":{\"timestamp\":1744116293,\"today_s\":3691},\"intervals\":[],\"lastCallbackAttempt\":1744116350,\"localStorageId\":\"22439590\",\"syncedL24HS\":null,\"syncedTodayS\":null}"
        },
        {
          "name": "last_headload_time",
          "value": "1744116353811"
        },
        {
          "name": "hb_timestamp",
          "value": "1744116326385"
        },
        {
          "name": "bdz_playback_state",
          "value": "{\"session_key\":\"m8u7fvcu\",\"buffer_length\":60}"
        },
        {
          "name": "mw_encrypted_backups_restore_upsell_first_impression_time_key",
          "value": "1744116350404"
        },
        {
          "name": "ares_last_signal_flush",
          "value": "1743252351870"
        },
        {
          "name": "signal_flush_timestamp",
          "value": "1744116326398"
        },
        {
          "name": "Session",
          "value": "8068ol:1744116450643"
        },
        {
          "name": "banzai:last_storage_flush",
          "value": "1744116326399.6"
        }
      ]
    }
  ]
}